zernpol/__init__.py
zernpol/_pupil.py
zernpol/_tools.py
zernpol/_zernpol.py
zernpol-0.1.5.dist-info/WHEEL
zernpol-0.1.5.dist-info/METADATA
zernpol-0.1.5.dist-info/RECORD
