Metadata-Version: 2.1
Name: zernpol
Version: 0.1.5
Summary: Tools to handle Zernike polynoms and Indexing systems
License: MIT
Author: Sylvain Guieu
Author-email: sylvain.guieu@univ-grenoble-alpes.fr
Requires-Python: >=3.6,<4.0
Classifier: License :: OSI Approved :: MIT License
Classifier: Programming Language :: Python :: 3
Classifier: Programming Language :: Python :: 3.6
Classifier: Programming Language :: Python :: 3.7
Classifier: Programming Language :: Python :: 3.8
Classifier: Programming Language :: Python :: 3.9
Classifier: Programming Language :: Python :: 3.10
Classifier: Programming Language :: Python :: 3.11
Requires-Dist: numpy (>=1.2,<2.0)
